fred_matt_merman/__init__.py
fred_matt_merman/database.py
fred_matt_merman/display.py
fred_matt_merman/request.py
fred_matt_merman-0.9.dist-info/METADATA
fred_matt_merman-0.9.dist-info/WHEEL
fred_matt_merman-0.9.dist-info/top_level.txt
fred_matt_merman-0.9.dist-info/RECORD
